bayan_address/__init__.py
bayan_address/main.py
bayan_address/lib/data.py
bayan_address/lib/errors.py
bayan_address/lib/helpers.py
bayan_address/lib/utils.py
bayan_address/parser/__init__.py
bayan_address/parser/core.py
bayan_address/parser/matchers.py
bayan_address-0.2.1.dist-info/LICENSE
bayan_address-0.2.1.dist-info/METADATA
bayan_address-0.2.1.dist-info/WHEEL
bayan_address-0.2.1.dist-info/top_level.txt
bayan_address-0.2.1.dist-info/RECORD
