Metadata-Version: 2.1
Name: bayan-address
Version: 0.2.1
Summary: A Python-based address parser for Philippines
Home-page: https://github.com/netervati/bayan_address
Author: Christopher Tabula
Author-email: netervati@gmail.com
License: MIT License
Classifier: Development Status :: 3 - Alpha
Classifier: Intended Audience :: Information Technology
Classifier: Intended Audience :: Science/Research
Classifier: License :: OSI Approved :: MIT License
Classifier: Operating System :: Microsoft :: Windows :: Windows 10
Classifier: Programming Language :: Python :: 3.9
License-File: LICENSE
